starlette_i18n/__init__.py
starlette_i18n/constants.py
starlette_i18n/context.py
starlette_i18n/helpers.py
starlette_i18n/i18n.py
starlette_i18n/locale.py
starlette_i18n/middleware.py
starlette_i18n/version.py
tests/__init__.py
tests/conftest.py
tests/constants.py
tests/messages.py
tests/test_constants.py
tests/test_helpers.py
tests/test_i18n.py
tests/test_locale.py
tests/test_middleware.py
starlette_i18n-2.1.0.dist-info/LICENSE
starlette_i18n-2.1.0.dist-info/METADATA
starlette_i18n-2.1.0.dist-info/WHEEL
starlette_i18n-2.1.0.dist-info/top_level.txt
starlette_i18n-2.1.0.dist-info/RECORD
